cs/fs.py
cs_fs-20250728.dist-info/WHEEL
cs_fs-20250728.dist-info/METADATA
cs_fs-20250728.dist-info/RECORD
