Metadata-Version: 2.4
Name: cs-fs
Version: 20250728
Summary: Assorted filesystem related utility functions, some of which have been bloating cs.fileutils for too long.
Keywords: python2,python3
Author-email: Cameron Simpson <cs@cskk.id.au>
Requires-Python: >=3.6
Classifier: Programming Language :: Python
Classifier: Programming Language :: Python :: 3
Classifier: Development Status :: 4 - Beta
Classifier: Intended Audience :: Developers
Classifier: Operating System :: OS Independent
Classifier: Topic :: Software Development :: Libraries :: Python Modules
Classifier: License :: OSI Approved :: GNU General Public License v3 or later (GPLv3+)
Requires-Dist: cs.deco>=20250724
Requires-Dist: cs.lex>=20250724
Requires-Dist: cs.obj>=20250306
Requires-Dist: cs.pfx>=20250613
Project-URL: MonoRepo Commits, https://bitbucket.org/cameron_simpson/css/commits/branch/main
Project-URL: Monorepo Git Mirror, https://github.com/cameron-simpson/css
Project-URL: Monorepo Hg/Mercurial Mirror, https://hg.sr.ht/~cameron-simpson/css
Project-URL: Source, https://github.com/cameron-simpson/css/blob/main/lib/python/cs/fs.py
